setup.py
django_comments_rss/__init__.py
django_comments_rss/feeds.py
django_comments_rss/urls.py
django_comments_rss.egg-info/PKG-INFO
django_comments_rss.egg-info/SOURCES.txt
django_comments_rss.egg-info/dependency_links.txt
django_comments_rss.egg-info/top_level.txt