Metadata-Version: 1.0
Name: django-comments-rss
Version: 0.1
Summary: RSS channel for django.contrib.comments. Designed for every content type.
Home-page: http://www.jarmalavicius.lt
Author: Remigijus Jarmalavicius
Author-email: remigijus@jarmalavicius.lt
License: BSD
Platform: UNKNOWN
